Workbook

Sheet Summary
B1: Energya Power Cables
B2: A Company Of Energya Cables
B3: Financial Department | S3: CLEVELAND | T3: USD
B4: EPC REF: | J4: Centeral Bank of Egypt date 19-08-2026 | S4: ELAND | T4: GBP
J5: USD Rate | K5: 50.6581 | S5: BATT | T5: Euro
C6: =IF($H$10="USD","Aluminum USD",IF($H$10="GBP","Aluminum GBP","Aluminum Euro")) -> Aluminum Euro | D6: 2800 | J6: Euro Rate | K6: 58.6164 | S6: PX KABEL
C7: =IF($H$10="USD","Copper USD",IF($H$10="GBP","Copper GBP","Copper Euro")) -> Copper Euro | D7: 12500 | J7: GBP Rate | K7: 68.51 | S7: ANIXTER
C8: Rate of Transfeer | D8: =IF(H10="USD",1,IF(H10="GBP",K7/K5,K6/K5)) -> 1.1570983 | J8: Operation Exp. | K8: 0
C9: Aluminum USD | D9: =D6*$D$8 -> 3239.8752 | J9: Finanace Cost | K9: 0
C10: Copper USD | D10: =($D$7)*$D$8 -> 14463.728 | H10: Euro | I10: 0.06 | J10: G&A & Marketing | K10: 0
B12: Ser | C12: Description | D12: Qty | E12: TYPE | F12: Material Number | G12: CU Weight KG/KM | H12: AL Weight KG/KM | I12: =IF($H$10="USD","Unit Price/USD",IF($H$10="GBP","Unit Price/GBP","Unit Price/Euro")) -> Unit Price/Euro | J12: =IF($H$10="USD","Total Value USD",IF($H$10="GBP","Total Value GBP","Total Value Euro")) -> Total Value Euro | K12: =IF($H$10="USD","Unit Cost/USD",IF($H$10="GBP","Unit Cost/GBP","Unit Cost/Euro")) -> Unit Cost/Euro | L12: =IF($H$10="USD","Total Cost/USD",IF($H$10="GBP","Total Cost/GBP","Total Cost/Euro")) -> Total Cost/Euro | M12: GM | N12: % | P12: CU MT | Q12: AL MT | S12: Material Margin | T12: KM/Month | U12: Total
B13: 1 | C13: ='1'!D6 -> Cu / XLPE / LSHF 0.6/1 kV 1X16 mm2 RMC IEC 60502-1 | D13: 1 | E13: =+'1'!$B$9 -> CU | F13: =+'1'!K4 -> 10009487 | G13: {=SUM( SUMIF( INDIRECT("'"&(ROW()-12)&"'!$C$9:$C$26"), {"cr01","ct02","CR02","CT04","CT05","CT01","ct03","ct06","ct13"}, INDIRECT("'"&(ROW()-12)&"'!$E$9:$E$26") ) )} -> 135.23 | H13: {=SUM( SUMIF( INDIRECT("'"&(ROW()-12)&"'!$C$9:$C$26"), {"AR01","AR08","AR10","AR02"}, INDIRECT("'"&(ROW()-12)&"'!$E$9:$E$26") ) )} -> 0 | I13: =K13/(100%-$I$10) -> 2379.822 | J13: =+I13*D13 -> 2379.822 | K13: =+'1'!K28 -> 2237.0327 | L13: =+K13*D13 -> 2237.0327 | M13: =J13-L13 -> 142.78932 | N13: =M13/J13 -> 0.06 | P13: =+D13*G13/1000 -> 0.13523 | Q13: =D13*H13/1000 -> 0 | S13: =I13-K13 -> 142.78932 | U13: =T13*S13 -> 0
B14: 2 | C14: ='2'!D6 -> Cu / XLPE / LSHF 0.6/1 kV 5X185 mm2 RMC IEC 60502-1 | D14: 1 | E14: =+'2'!$B$9 -> CU | F14: =+'2'!K4 -> 10009546 | G14: {=SUM( SUMIF( INDIRECT("'"&(ROW()-12)&"'!$C$9:$C$26"), {"cr01","ct02","CR02","CT04","CT05","CT01","ct03","ct06","ct13"}, INDIRECT("'"&(ROW()-12)&"'!$E$9:$E$26") ) )} -> 8217.45 | H14: {=SUM( SUMIF( INDIRECT("'"&(ROW()-12)&"'!$C$9:$C$26"), {"AR01","AR08","AR10","AR02"}, INDIRECT("'"&(ROW()-12)&"'!$E$9:$E$26") ) )} -> 0 | I14: =K14/(100%-$I$10) -> 121195.43 | J14: =+I14*D14 -> 121195.43 | K14: =+'2'!$K$32 -> 113923.71 | L14: =+K14*D14 -> 113923.71 | M14: =J14-L14 -> 7271.7259 | N14: =M14/J14 -> 0.06 | P14: =+D14*G14/1000 -> 8.21745 | Q14: =D14*H14/1000 -> 0 | S14: =I14-K14 -> 7271.7259 | U14: =T14*S14 -> 0
B15: 3 | C15: ='3'!D6 -> Al / XLPE / MDPE 18/30 kV CWs 1X300/25 mm2 RMC IEC 60502-2 | D15: 1 | E15: =+'3'!$B$9 -> Al | F15: =+'3'!K4 -> 10010347 | G15: {=SUM( SUMIF( INDIRECT("'"&(ROW()-12)&"'!$C$9:$C$26"), {"cr01","ct02","CR02","CT04","CT05","CT01","ct03","ct06","ct13"}, INDIRECT("'"&(ROW()-12)&"'!$E$9:$E$26") ) )} -> 0 | H15: {=SUM( SUMIF( INDIRECT("'"&(ROW()-12)&"'!$C$9:$C$26"), {"AR01","AR08","AR10","AR02"}, INDIRECT("'"&(ROW()-12)&"'!$E$9:$E$26") ) )} -> 788.83 | I15: =K15/(100%-$I$10) -> 6998.2385 | J15: =+I15*D15 -> 6998.2385 | K15: =+'3'!$K$32 -> 6578.3442 | L15: =+K15*D15 -> 6578.3442 | M15: =J15-L15 -> 419.89431 | N15: =M15/J15 -> 0.06 | P15: =+D15*G15/1000 -> 0 | Q15: =D15*H15/1000 -> 0.78883 | S15: =I15-K15 -> 419.89431 | U15: =T15*S15 -> 0
B16: 4 | C16: ='4'!D6 -> Cu / XLPE / MDPE 8.7/15 kV CWs 1X400/35 mm2 RMC IEC 60502-2 | D16: 1 | E16: =+'4'!$B$9 -> CU | F16: =+'4'!K4 -> 10010439 | G16: =+'4'!E9+'4'!E19 -> 3700.36 | H16: {=SUM( SUMIF( INDIRECT("'"&(ROW()-12)&"'!$C$9:$C$26"), {"AR01","AR08","AR10","AR02"}, INDIRECT("'"&(ROW()-12)&"'!$E$9:$E$26") ) )} -> 0 | I16: =K16/(100%-$I$10) -> 62186.116 | J16: =+I16*D16 -> 62186.116 | K16: =+'4'!$K$32 -> 58454.949 | L16: =+K16*D16 -> 58454.949 | M16: =J16-L16 -> 3731.167 | N16: =M16/J16 -> 0.06 | P16: =+D16*G16/1000 -> 3.70036 | Q16: =D16*H16/1000 -> 0 | S16: =I16-K16 -> 3731.167 | U16: =T16*S16 -> 0
B17: Grand Total Ex-Work Cost | J17: =SUM(J13:J16) -> 192759.61 | L17: =SUM(L13:L16) -> 181194.03 | M17: =SUM(M13:M16) -> 11565.577 | N17: =M17/J17 -> 0.06 | P17: =SUM(P13:P16) -> 12.05304 | Q17: =SUM(Q13:Q16) -> 0.78883
B18: Shipping cost | J18: =+L23 -> 3603.0867 | L18: =+L23 -> 3603.0867 | M18: =J18-L18 -> 0 | N18: =M18/J18 -> 0
B19: Grand Total Include Shipping Cost | J19: =SUM(J17:J18) -> 196362.7 | L19: =+L17+L23 -> 184797.12 | M19: =+J19-L19 -> 11565.577 | N19: =M19/J19 -> 0.058899052
C21: Customer: | D21: ELAND | J21: Shipping Cost :-
C22: Delivered to: DAP - | D22: Doncaster | J22: =IF(D22="FOB","FOB COST",IF(D22="EX WORK","EX WORK COST","DAP COST")) -> DAP COST | K22: =L26 -> 3024.8079 | L22: =IF(D22="FOB",K22,IF(D22="EX WORK",K22,+K22+(J17*0.003))) -> 3603.0867 | M22: =L22/J17 -> 0.018692125
C23: No.of container 20 | D23: 0 | J23: Total Shipping Cost | L23: =+L22 -> 3603.0867
C24: No.of container 40 | D24: =+J25 -> 1
I25: Cont 40' ST | J25: 1 | K25: =3500/D8 -> 3024.8079 | L25: =J25*K25 -> 3024.8079
I26: Total | L26: =SUM(L25:L25) -> 3024.8079

Sheet Materials List
B3: 0 | D3: Rate | E3: =Summary!K6 -> 58.6164 | F3: =Summary!K5 -> 50.6581
B5: Material Code | C5: Material description | D5: Unit Cost | E5: Currency | F5: Unit Cost L.E | H5: =B5 -> Material Code | I5: Scrap %
B6: CR01 | C6: Copper Rod "8mm" | D6: =Summary!D10 -> 14463.728 | E6: USD | F6: =(D6+505+50)*(100%+B3)*$F$3/1000 -> 760.82025 | H6: =B6 -> CR01 | I6: 0.01
B7: AR01 | C7: Aluminum Rod H12 "9 mm" | D7: =Summary!D9 -> 3239.8752 | E7: USD | F7: =(D7+725+50)*1*$F$3/1000 -> 203.38595 | H7: =B7 -> AR01 | I7: 0.01
B8: CuT02 | C8: Copper Tape 10x0.1mm | D8: =Summary!$D$10 -> 14463.728 | E8: USD | F8: =(D8+1200+50)*1*$F$3/1000 -> 796.02762 | H8: =B8 -> CuT02 | I8: 0.01
B9: TP01 | C9: Chalk Powder | D9: 12600 | E9: LE | F9: =D9/1000 -> 12.6 | H9: =B9 -> TP01 | I9: 0.01
B10: RC03 | C10: RIP CORD | D10: 150000 | E10: LE | F10: =D10/1000 -> 150 | H10: =B10 -> RC03 | I10: 0.01
B11: HB02 | C11: Sheath Bedding | D11: =1360+100 -> 1460 | E11: Euro | F11: =+D11*$E$3/1000 -> 85.579944 | H11: =B11 -> HB02 | I11: 0.01
B12: HF30 | C12: Thermosetting compound Low smoke halogen free | D12: =2500+100 -> 2600 | E12: Euro | F12: =+D12*E3/1000 -> 152.40264 | H12: =B12 -> HF30 | I12: 0.01
B13: HF27 | C13: Thermosetting compound Low smoke halogen free | D13: =4000+100 -> 4100 | E13: Euro | F13: =+D13*E3/1000 -> 240.32724 | H13: =B13 -> HF27 | I13: 0.01
B14: YN01 | C14: Water blocking yarn 3WY055 Tapes | D14: =17100+100 -> 17200 | E14: Euro | F14: =(D14*$E$3*1.1)/1000 -> 1109.0223 | H14: =B14 -> YN01 | I14: 0.01
B15: AFD155 | C15: Laminted Aluminum TAPE | D15: =4600+50 -> 4650 | E15: USD | F15: =(D15*$F$3*1.05)/1000 -> 247.33817 | H15: =B15 -> AFD155 | I15: 0.01
B16: AFD145 | C16: Laminted Aluminum TAPE | D16: =4600+50 -> 4650 | E16: USD | F16: =(D16*$F$3*1.05)/1000 -> 247.33817 | H16: =B16 -> AFD145 | I16: 0.01
B17: A-ECAP10 | C17: A-ECAP10 | D17: 200000 | E17: LE | F17: =D17/1000 -> 200 | H17: =B17 -> A-ECAP10 | I17: 0.01
B18: A-EC05 | C18: A-ECAP10 | D18: 200000 | E18: LE | F18: =D18/1000 -> 200 | H18: =B18 -> A-EC05 | I18: 0.01
B19: A-EC04 | C19: A-ECAP10 | D19: 200000 | E19: LE | F19: =D19/1000 -> 200 | H19: =B19 -> A-EC04 | I19: 0.01
B20: ML04 | C20: Color Master Batch for LSHF | D20: =10000+100 -> 10100 | E20: USD | F20: =+D20*$F$3*1.1/1000 -> 562.81149 | H20: =B20 -> ML04 | I20: 0.01
B21: SC01 | C21: Thermosetting S.C - Bonded | D21: =1900+100+100 -> 2100 | E21: USD | F21: =D21*1*$F$3/1000 -> 106.38201 | H21: =B21 -> SC01 | I21: 0.01
B22: SC02 | C22: Thermosetting S.C - Strippable | D22: =2355+100 -> 2455 | E22: USD | F22: =D22*1*$F$3/1000 -> 124.36564 | H22: =B22 -> SC02 | I22: 0.01
B23: XL02 | C23: XLPE Insulation For M.V Cable | D23: =2030+100+100 -> 2230 | E23: USD | F23: =D23*1*$F$3/1000 -> 112.96756 | H23: =B23 -> XL02 | I23: 0.01
B24: PS03 | C24: Medium density PE Sheath "Black" | D24: =1400+100+100 -> 1600 | E24: USD | F24: =D24*1*$F$3/1000 -> 81.05296 | H24: =B24 -> PS03 | I24: 0.01
B25: WS03 | C25: Semi-conductive Water Blocking | D25: =807+100+100 -> 1007 | E25: USD | F25: =D25*$F$3*1.1/1000 -> 56.113977 | H25: =B25 -> WS03 | I25: 0.01
B26: WS01 | C26: Semi-conductive Water Blocking | D26: =2180+100+100 -> 2380 | E26: USD | F26: =D26*1.1*$F$3/1000 -> 132.62291 | H26: =B26 -> WS01 | I26: 0.01
B27: WN35 | C27: Non-Conductive Water Blocking | D27: =380+100+250 -> 730 | E27: USD | F27: =D27*1.1*$F$3/1000 -> 40.678454 | H27: =B27 -> WN35 | I27: 0.01
B28: WN65 | C28: Non-Conductive Water Blocking | D28: =350+100+250 -> 700 | E28: USD | F28: =D28*1.1*$F$3/1000 -> 39.006737 | H28: =B28 -> WN65 | I28: 0.01
B29: WN03 | C29: Non-Conductive Water Blocking | D29: =650+100+100 -> 850 | E29: USD | F29: =D29*1.1*$F$3/1000 -> 47.365324 | H29: =B29 -> WN03 | I29: 0.01
B30: WN08 | C30: Non-Conductive Water Blocking | D30: =250+100+250 -> 600 | E30: USD | F30: =D30*1.1*$F$3/1000 -> 33.434346 | H30: =B30 -> WN08 | I30: 0.01
B31: WN75 | C31: Non-Conductive Water Blocking | D31: =360+100+100 -> 560 | E31: USD | F31: =D31*1.1*$F$3/1000 -> 31.20539 | H31: =B31 -> WN75 | I31: 0.01
B32: WN81 | C32: Non-Conductive Water Blocking | D32: =650+100+100 -> 850 | E32: USD | F32: =D32*1.1*$F$3/1000 -> 47.365324 | H32: =B32 -> WN81 | I32: 0.01
B33: XL08 | C33: XLPE Insulation ForBasec | D33: =1800+100 -> 1900 | E33: USD | F33: =D33*$F$3/1000 -> 96.25039 | H33: =B33 -> XL08 | I33: 0.01
B34: CX05 | C34: Catalyst for PE insulation mat | D34: =4500+100 -> 4600 | E34: USD | F34: =D34*$F$3/1000 -> 233.02726 | H34: =B34 -> CX05 | I34: 0.01
B35: PT04 | C35: Poly Propylene Tape "40 X 0.125 mm" | D35: =2700+100+100 -> 2900 | E35: USD | F35: =D35*1*$F$3/1000 -> 146.90849 | H35: =B35 -> PT04 | I35: 0.01
B36: PT06 | C36: Polyproplyene TAPE "60 X 0.125 mm" | D36: =2700+100+100 -> 2900 | E36: USD | F36: =D36*1*$F$3/1000 -> 146.90849 | H36: =B36 -> PT06 | I36: 0.01
B37: MP02 | C37: Color Master Batch for XLPE in | D37: 197500 | E37: LE | F37: =+D37/1000 -> 197.5 | H37: =B37 -> MP02 | I37: 0.01
B38: MP04 | C38: Color Master Batch for XLPE in | D38: 192000 | E38: LE | F38: =+D38/1000 -> 192 | H38: =B38 -> MP04 | I38: 0.01
B39: MP03 | C39: Color Master Batch for XLPE in | D39: 206000 | E39: LE | F39: =+D39/1000 -> 206 | H39: =B39 -> MP03 | I39: 0.01
B40: MP06 | C40: Color Master Batch for XLPE in | D40: 206000 | E40: LE | F40: =+D40/1000 -> 206 | H40: =B40 -> MP06 | I40: 0.01
B41: MP07 | C41: Color Master Batch for XLPE in | D41: 189000 | E41: LE | F41: =+D41/1000 -> 189 | H41: =B41 -> MP07 | I41: 0.01
B42: MP05 | C42: Color Master Batch for XLPE in | D42: 168000 | E42: LE | F42: =+D42/1000 -> 168 | H42: =B42 -> MP05 | I42: 0.01

Sheet 1
D2: Aluminum | E2: =Summary!$D$9 -> 3239.8752
D3: Copper | E3: =Summary!$D$10 -> 14463.728
D4: =IF(Summary!H10="USD","USD Rate",IF(Summary!H10="Euro","Euro Rate","GBP Rate")) -> Euro Rate | E4: =IF(Summary!H10="USD",Summary!K5,IF(Summary!H10="GBP",Summary!K7,Summary!K6)) -> 58.6164 | J4: Cable Material Number | K4: 10009487
D6: Cu / XLPE / LSHF 0.6/1 kV 1X16 mm2 RMC IEC 60502-1 | J6: Qty Required | K6: =Summary!D13 -> 1
C8: Material Code | D8: Materails Description | E8: Standard Qty | F8: Scrap % | G8: Qty with Scrap Allow. | H8: Unit Price L.E | I8: =IF(Summary!H10="USD","Unit Price USD",IF(Summary!H10="GBP","Unit Price GBP","Unit Price Euro")) -> Unit Price Euro | J8: Value L.E | K8: =IF(Summary!H10="USD","Value USD",IF(Summary!H10="GBP","Value GBP","Value Euro")) -> Value Euro | L8: %
B9: =+IF(C9="CR01","CU",IF(C9="CR02","CU",IF(C9="AR01","AL",IF(C9="AR02","AL",IF(C9="AR08","AL",IF(C9="AR03","AL")))))) -> CU | C9: CR01 | D9: =VLOOKUP(C9,'Materials List'!$B$6:$F$42,2,0) -> Copper Rod "8mm" | E9: 135.23 | F9: =VLOOKUP(C9,'Materials List'!$H$6:I$359,2,0) -> 0.01 | G9: =E9+(E9*F9) -> 136.5823 | H9: =VLOOKUP(C9,'Materials List'!$B$6:$F$53,5,0) -> 760.82025 | I9: =H9/$E$4 -> 12.979648 | J9: =G9*H9 -> 103914.58 | K9: =I9*G9 -> 1772.7902 | L9: =J9/$J$28 -> 0.79247398
C10: XL08 | D10: =VLOOKUP(C10,'Materials List'!$B$6:$F$42,2,0) -> XLPE Insulation ForBasec | E10: 11.92 | F10: =VLOOKUP(C10,'Materials List'!$H$6:$I$359,2,0) -> 0.01 | G10: =E10+(E10*F10) -> 12.0392 | H10: =VLOOKUP(C10,'Materials List'!$B$6:$F$53,5,0) -> 96.25039 | I10: =H10/$E$4 -> 1.6420386 | J10: =G10*H10 -> 1158.7777 | K10: =I10*G10 -> 19.768831 | L10: =J10/$J$28 -> 0.0088370773
C11: CX05 | D11: =VLOOKUP(C11,'Materials List'!$B$6:$F$42,2,0) -> Catalyst for PE insulation mat | E11: 0.61 | F11: =VLOOKUP(C11,'Materials List'!$H$6:$I$359,2,0) -> 0.01 | G11: =E11+(E11*F11) -> 0.6161 | H11: =VLOOKUP(C11,'Materials List'!$B$6:$F$53,5,0) -> 233.02726 | I11: =H11/$E$4 -> 3.9754618 | J11: =G11*H11 -> 143.56809 | K11: =I11*G11 -> 2.449282 | L11: =J11/$J$28 -> 0.0010948799
C12: TP01 | D12: =VLOOKUP(C12,'Materials List'!$B$6:$F$42,2,0) -> Chalk Powder | E12: 0.5 | F12: =VLOOKUP(C12,'Materials List'!$H$6:$I$359,2,0) -> 0.01 | G12: =E12+(E12*F12) -> 0.505 | H12: =VLOOKUP(C12,'Materials List'!$B$6:$F$53,5,0) -> 12.6 | I12: =H12/$E$4 -> 0.21495691 | J12: =G12*H12 -> 6.363 | K12: =I12*G12 -> 0.10855324 | L12: =J12/$J$28 -> 4.8525548e-05
C13: HF30 | D13: =VLOOKUP(C13,'Materials List'!$B$6:$F$42,2,0) -> Thermosetting compound Low smoke halogen free | E13: 45.2 | F13: =VLOOKUP(C13,'Materials List'!$H$6:$I$359,2,0) -> 0.01 | G13: =E13+(E13*F13) -> 45.652 | H13: =VLOOKUP(C13,'Materials List'!$B$6:$F$53,5,0) -> 152.40264 | I13: =H13/$E$4 -> 2.6 | J13: =G13*H13 -> 6957.4853 | K13: =I13*G13 -> 118.6952 | L13: =J13/$J$28 -> 0.053059216
C14: HF27 | D14: =VLOOKUP(C14,'Materials List'!$B$6:$F$42,2,0) -> Thermosetting compound Low smoke halogen free | E14: 72.9 | F14: =VLOOKUP(C14,'Materials List'!$H$6:$I$359,2,0) -> 0.01 | G14: =E14+(E14*F14) -> 73.629 | H14: =VLOOKUP(C14,'Materials List'!$B$6:$F$53,5,0) -> 240.32724 | I14: =H14/$E$4 -> 4.1 | J14: =G14*H14 -> 17695.054 | K14: =I14*G14 -> 301.8789 | L14: =J14/$J$28 -> 0.13494613
C15: ML04 | D15: =VLOOKUP(C15,'Materials List'!$B$6:$F$42,2,0) -> Color Master Batch for LSHF | E15: 1.49 | F15: =VLOOKUP(C15,'Materials List'!$H$6:$I$359,2,0) -> 0.01 | G15: =E15+(E15*F15) -> 1.5049 | H15: =VLOOKUP(C15,'Materials List'!$B$6:$F$53,5,0) -> 562.81149 | I15: =H15/$E$4 -> 9.6016045 | J15: =G15*H15 -> 846.97501 | K15: =I15*G15 -> 14.449455 | L15: =J15/$J$28 -> 0.0064592059
C16: A-ECAP10 | D16: =VLOOKUP(C16,'Materials List'!$B$6:$F$42,2,0) -> A-ECAP10 | E16: 2 | F16: =VLOOKUP(C16,'Materials List'!$H$6:$I$359,2,0) -> 0.01 | G16: =E16+(E16*F16) -> 2.02 | H16: =VLOOKUP(C16,'Materials List'!$B$6:$F$53,5,0) -> 200 | I16: =H16/$E$4 -> 3.4120144 | J16: =G16*H16 -> 404 | K16: =I16*G16 -> 6.8922691 | L16: =J16/$J$28 -> 0.0030809872
G23: 0 | H23: 0 | I23: =H23/$E$4 -> 0 | J23: =H23*G23 -> 0 | K23: =I23*G23 -> 0 | L23: =J23/$J$28 -> 0
C24: Total Materials Cost | J24: =SUM(J9:J23) -> 131126.8 | K24: =SUM(K9:K23) -> 2237.0327 | L24: =SUM(L9:L23) -> 1
C25: MOH | J25: =+J24*Summary!$K$8 -> 0 | K25: =J25/$E$4 -> 0 | L25: =J25/J28 -> 0
C26: Finanace Cost | J26: =J24*Summary!$K$9 -> 0 | K26: =J26/$E$4 -> 0 | L26: =J26/$J$28 -> 0 | N26: Sales Price
C27: G&A & Marketing | J27: =J24*Summary!$K$10 -> 0 | K27: =J27/$E$4 -> 0 | L27: =J27/$J$28 -> 0 | N27: Net Profit | O27: =O26-K28 -> -2237.0327
C28: Total Cable Cost | J28: =SUM(J24:J27) -> 131126.8 | K28: =SUM(K24:K27) -> 2237.0327 | L28: =SUM(L24:L27) -> 1 | N28: % | O28: =O27/O26 -> #DIV/0!
F30: Size | G30: N.of drum | H30: length | I30: price | J30: total length | K30: Total value
G31: 0 | H31: 0 | I31: =IF($N$23="Supported",VLOOKUP(F31,#REF!,2,0)*1.25,VLOOKUP(F31,#REF!,2,0)) -> #REF! | J31: =H31*G31 -> 0 | K31: =I31*G31 -> #REF!
G32: 0 | H32: 0 | I32: =IF($N$23="Supported",VLOOKUP(F32,#REF!,2,0)*1.25,VLOOKUP(F32,#REF!,2,0)) -> #REF! | J32: =H32*G32 -> 0 | K32: =I32*G32 -> #REF!
J33: =SUM(J31:J32) -> 0 | K33: =SUM(K31:K32) -> #REF!
K34: =K33/J33*1000 -> #REF!
D35: Study | E35: Qty/KM | F35: Scrap Qty | G35: Scrap Qty
D36: Cutting Length | F36: =E36/1000*(2000-H31) -> 0 | G36: =+F36/E36 -> #DIV/0!
D37: Cutting Length | F37: =E37/1000*(2000-H32) -> 0 | G37: =+F37/E37 -> #DIV/0!
D38: Total Qty Required | E38: =+E37*K6 -> 0 | F38: =+SUM(F36:F37) -> 0 | G38: =+F38/E38 -> #DIV/0!

Sheet 2
D2: Aluminum | E2: =Summary!$D$9 -> 3239.8752
D3: Copper | E3: =Summary!$D$10 -> 14463.728
D4: =IF(Summary!H10="USD","USD Rate",IF(Summary!H10="Euro","Euro Rate","GBP Rate")) -> Euro Rate | E4: =IF(Summary!H10="USD",Summary!K5,IF(Summary!H10="GBP",Summary!K7,Summary!K6)) -> 58.6164 | J4: Cable Material Number | K4: 10009546
D6: Cu / XLPE / LSHF 0.6/1 kV 5X185 mm2 RMC IEC 60502-1 | J6: Qty Required | K6: =Summary!D14 -> 1
C8: Material Code | D8: Materails Description | E8: Standard Qty | F8: Scrap % | G8: Qty with Scrap Allow. | H8: Unit Price L.E | I8: =IF(Summary!H10="USD","Unit Price USD",IF(Summary!H10="GBP","Unit Price GBP","Unit Price Euro")) -> Unit Price Euro | J8: Value L.E | K8: =IF(Summary!H10="USD","Value USD",IF(Summary!H10="GBP","Value GBP","Value Euro")) -> Value Euro | L8: %
B9: =+IF(C9="CR01","CU",IF(C9="CR02","CU",IF(C9="AR01","AL",IF(C9="AR02","AL",IF(C9="AR08","AL",IF(C9="AR03","AL")))))) -> CU | C9: CR01 | D9: =VLOOKUP(C9,'Materials List'!$B$6:$F$42,2,0) -> Copper Rod "8mm" | E9: 8217.45 | F9: 0.01 | G9: =E9+(E9*F9) -> 8299.6245 | H9: =VLOOKUP(C9,'Materials List'!$B$6:$F$53,5,0) -> 760.82025 | I9: =H9/$E$4 -> 12.979648 | J9: =G9*H9 -> 6314522.3 | K9: =I9*G9 -> 107726.21 | L9: =J9/$J$32 -> 0.94559955
C10: XL08 | D10: =VLOOKUP(C10,'Materials List'!$B$6:$F$42,2,0) -> XLPE Insulation ForBasec | E10: 420.76 | F10: 0.01 | G10: =E10+(E10*F10) -> 424.9676 | H10: =VLOOKUP(C10,'Materials List'!$B$6:$F$53,5,0) -> 96.25039 | I10: =H10/$E$4 -> 1.6420386 | J10: =G10*H10 -> 40903.297 | K10: =I10*G10 -> 697.81319 | L10: =J10/$J$32 -> 0.0061252677
C11: CX05 | D11: =VLOOKUP(C11,'Materials List'!$B$6:$F$42,2,0) -> Catalyst for PE insulation mat | E11: 22.15 | F11: 0.01 | G11: =E11+(E11*F11) -> 22.3715 | H11: =VLOOKUP(C11,'Materials List'!$B$6:$F$53,5,0) -> 233.02726 | I11: =H11/$E$4 -> 3.9754618 | J11: =G11*H11 -> 5213.1693 | K11: =I11*G11 -> 88.937044 | L11: =J11/$J$32 -> 0.00078067197
C12: TP01 | D12: =VLOOKUP(C12,'Materials List'!$B$6:$F$42,2,0) -> Chalk Powder | E12: 2.5 | F12: 0.01 | G12: =E12+(E12*F12) -> 2.525 | H12: =VLOOKUP(C12,'Materials List'!$B$6:$F$53,5,0) -> 12.6 | I12: =H12/$E$4 -> 0.21495691 | J12: =G12*H12 -> 31.815 | K12: =I12*G12 -> 0.54276619 | L12: =J12/$J$32 -> 4.7642954e-06
C13: HB02 | D13: =VLOOKUP(C13,'Materials List'!$B$6:$F$42,2,0) -> Sheath Bedding | E13: 270.61 | F13: 0.01 | G13: =E13+(E13*F13) -> 273.3161 | H13: =VLOOKUP(C13,'Materials List'!$B$6:$F$53,5,0) -> 85.579944 | I13: =H13/$E$4 -> 1.46 | J13: =G13*H13 -> 23390.377 | K13: =I13*G13 -> 399.04151 | L13: =J13/$J$32 -> 0.0035027083
C14: MP03 | D14: =VLOOKUP(C14,'Materials List'!$B$6:$F$42,2,0) -> Color Master Batch for XLPE in | E14: 0.85 | F14: 0.01 | G14: =E14+(E14*F14) -> 0.8585 | H14: =VLOOKUP(C14,'Materials List'!$B$6:$F$53,5,0) -> 206 | I14: =H14/$E$4 -> 3.5143748 | J14: =G14*H14 -> 176.851 | K14: =I14*G14 -> 3.0170908 | L14: =J14/$J$32 -> 2.6483433e-05
C15: MP06 | D15: =VLOOKUP(C15,'Materials List'!$B$6:$F$42,2,0) -> Color Master Batch for XLPE in | E15: 0.85 | F15: 0.01 | G15: =E15+(E15*F15) -> 0.8585 | H15: =VLOOKUP(C15,'Materials List'!$B$6:$F$53,5,0) -> 206 | I15: =H15/$E$4 -> 3.5143748 | J15: =G15*H15 -> 176.851 | K15: =I15*G15 -> 3.0170908 | L15: =J15/$J$32 -> 2.6483433e-05
C16: MP04 | D16: =VLOOKUP(C16,'Materials List'!$B$6:$F$42,2,0) -> Color Master Batch for XLPE in | E16: 0.85 | F16: 0.01 | G16: =E16+(E16*F16) -> 0.8585 | H16: =VLOOKUP(C16,'Materials List'!$B$6:$F$53,5,0) -> 192 | I16: =H16/$E$4 -> 3.2755338 | J16: =G16*H16 -> 164.832 | K16: =I16*G16 -> 2.8120458 | L16: =J16/$J$32 -> 2.4683588e-05
C17: MP05 | D17: =VLOOKUP(C17,'Materials List'!$B$6:$F$42,2,0) -> Color Master Batch for XLPE in | E17: 0.85 | F17: 0.01 | G17: =E17+(E17*F17) -> 0.8585 | H17: =VLOOKUP(C17,'Materials List'!$B$6:$F$53,5,0) -> 168 | I17: =H17/$E$4 -> 2.8660921 | J17: =G17*H17 -> 144.228 | K17: =I17*G17 -> 2.4605401 | L17: =J17/$J$32 -> 2.1598139e-05
C18: MP02 | D18: =VLOOKUP(C18,'Materials List'!$B$6:$F$42,2,0) -> Color Master Batch for XLPE in | E18: 0.6 | F18: 0.01 | G18: =E18+(E18*F18) -> 0.606 | H18: =VLOOKUP(C18,'Materials List'!$B$6:$F$53,5,0) -> 197.5 | I18: =H18/$E$4 -> 3.3693642 | J18: =G18*H18 -> 119.685 | K18: =I18*G18 -> 2.0418347 | L18: =J18/$J$32 -> 1.7922826e-05
C19: MP07 | D19: =VLOOKUP(C19,'Materials List'!$B$6:$F$42,2,0) -> Color Master Batch for XLPE in | E19: 0.26 | F19: 0.01 | G19: =E19+(E19*F19) -> 0.2626 | H19: =VLOOKUP(C19,'Materials List'!$B$6:$F$53,5,0) -> 189 | I19: =H19/$E$4 -> 3.2243536 | J19: =G19*H19 -> 49.6314 | K19: =I19*G19 -> 0.84671525 | L19: =J19/$J$32 -> 7.4323008e-06
C20: HB02 | D20: =VLOOKUP(C20,'Materials List'!$B$6:$F$42,2,0) -> Sheath Bedding | E20: 1471 | F20: 0.01 | G20: =E20+(E20*F20) -> 1485.71 | H20: =VLOOKUP(C20,'Materials List'!$B$6:$F$53,5,0) -> 85.579944 | I20: =H20/$E$4 -> 1.46 | J20: =G20*H20 -> 127146.98 | K20: =I20*G20 -> 2169.1366 | L20: =J20/$J$32 -> 0.019040257
C21: HF30 | D21: =VLOOKUP(C21,'Materials List'!$B$6:$F$42,2,0) -> Thermosetting compound Low smoke halogen free | E21: 583 | F21: 0.01 | G21: =E21+(E21*F21) -> 588.83 | H21: =VLOOKUP(C21,'Materials List'!$B$6:$F$53,5,0) -> 152.40264 | I21: =H21/$E$4 -> 2.6 | J21: =G21*H21 -> 89739.247 | K21: =I21*G21 -> 1530.958 | L21: =J21/$J$32 -> 0.01343845
... C24: A-EC05 | D24: =VLOOKUP(C24,'Materials List'!$B$6:$F$42,2,0) -> A-ECAP10 | E24: 2 | F24: 0.01 | G24: =E24+(E24*F24) -> 2.02 | H24: =VLOOKUP(C24,'Materials List'!$B$6:$F$53,5,0) -> 200 | I24: =H24/$E$4 -> 3.4120144 | J24: =G24*H24 -> 404 | K24: =I24*G24 -> 6.8922691 | L24: =J24/$J$32 -> 6.0498989e-05
I27: =H27/$E$4 -> 0 | J27: =H27*G27 -> 0 | K27: =I27*G27 -> 0 | L27: =J27/$J$32 -> 0
C28: Total Materials Cost | J28: =SUM(J9:J27) -> 6677797.5 | K28: =SUM(K9:K27) -> 113923.71 | L28: =SUM(L9:L27) -> 1
C29: MOH | J29: =+J28*Summary!$K$8 -> 0 | K29: =J29/$E$4 -> 0 | L29: =J29/J32 -> 0
C30: Finanace Cost | J30: =J28*Summary!$K$9 -> 0 | K30: =J30/$E$4 -> 0 | L30: =J30/$J$32 -> 0 | N30: Sales Price
C31: G&A & Marketing | J31: =J28*Summary!$K$10 -> 0 | K31: =J31/$E$4 -> 0 | L31: =J31/$J$32 -> 0 | N31: Net Profit | O31: =O30-K32 -> -113923.71
C32: Total Cable Cost | J32: =SUM(J28:J31) -> 6677797.5 | K32: =SUM(K28:K31) -> 113923.71 | L32: =SUM(L28:L31) -> 1 | N32: % | O32: =O31/O30 -> #DIV/0!
F34: Size | G34: N.of drum | H34: length | I34: price | J34: total length | K34: Total value
G35: 0 | H35: 0 | I35: =IF($N$27="Supported",VLOOKUP(F35,#REF!,2,0)*1.25,VLOOKUP(F35,#REF!,2,0)) -> #REF! | J35: =H35*G35 -> 0 | K35: =I35*G35 -> #REF!
G36: 0 | H36: 0 | I36: =IF($N$27="Supported",VLOOKUP(F36,#REF!,2,0)*1.25,VLOOKUP(F36,#REF!,2,0)) -> #REF! | J36: =H36*G36 -> 0 | K36: =I36*G36 -> #REF!
J37: =SUM(J35:J36) -> 0 | K37: =SUM(K35:K36) -> #REF!
K38: =K37/J37*1000 -> #REF!
D39: Study | E39: Qty/KM | F39: Scrap Qty | G39: Scrap Qty
D40: Cutting Length | F40: =E40/1000*(2000-H35) -> 0 | G40: =+F40/E40 -> #DIV/0!
D41: Cutting Length | F41: =E41/1000*(2000-H36) -> 0 | G41: =+F41/E41 -> #DIV/0!
D42: Total Qty Required | E42: =+E41*K6 -> 0 | F42: =+SUM(F40:F41) -> 0 | G42: =+F42/E42 -> #DIV/0!

Sheet 3
D2: Aluminum | E2: =Summary!$D$9 -> 3239.8752
D3: Copper | E3: =Summary!$D$10 -> 14463.728
D4: =IF(Summary!H10="USD","USD Rate",IF(Summary!H10="Euro","Euro Rate","GBP Rate")) -> Euro Rate | E4: =IF(Summary!H10="USD",Summary!K5,IF(Summary!H10="GBP",Summary!K7,Summary!K6)) -> 58.6164 | J4: Cable Material Number | K4: 10010347 | P4: Order Qty | Q4: Cutting Length
D6: Al / XLPE / MDPE 18/30 kV CWs 1X300/25 mm2 RMC IEC 60502-2 | J6: Qty Required | K6: =Summary!D15 -> 1 | P6: =+K6*1000 -> 1000 | Q6: =+E27 -> 1000
C8: Material Code | D8: Materails Description | E8: Standard Qty | F8: Scrap % | G8: Qty with Scrap Allow. | H8: Unit Price L.E | I8: =IF(Summary!H10="USD","Unit Price USD",IF(Summary!H10="GBP","Unit Price GBP","Unit Price Euro")) -> Unit Price Euro | J8: Value L.E | K8: =IF(Summary!H10="USD","Value USD",IF(Summary!H10="GBP","Value GBP","Value Euro")) -> Value Euro | L8: % | N8: New Scrap % | P8: New Scrap %
B9: Al | C9: YN01 | D9: =VLOOKUP(C9,'Materials List'!$B$6:$F$42,2,0) -> Water blocking yarn 3WY055 Tapes | E9: 5 | F9: =+R9 -> 0.156 | G9: =E9+(E9*F9) -> 5.78 | H9: =VLOOKUP(C9,'Materials List'!$B$6:$F$53,5,0) -> 1109.0223 | I9: =H9/$E$4 -> 18.92 | J9: =G9*H9 -> 6410.1488 | K9: =I9*G9 -> 109.3576 | L9: =J9/$J$32 -> 0.016623879 | N9: 40m/(Total Order Quantity * 3) | O9: Cu | P9: =40/(P6*1) -> 0.04 | Q9: CU | R9: =P9+P11+P16+P26 -> 0.156
C10: AR01 | D10: =VLOOKUP(C10,'Materials List'!$B$6:$F$42,2,0) -> Aluminum Rod H12 "9 mm" | E10: 788.83 | F10: =+R16 -> 0.006 | G10: =E10+(E10*F10) -> 793.56298 | H10: =VLOOKUP(C10,'Materials List'!$B$6:$F$53,5,0) -> 203.38595 | I10: =H10/$E$4 -> 3.4697789 | J10: =G10*H10 -> 161399.56 | K10: =I10*G10 -> 2753.4881 | L10: =J10/$J$32 -> 0.41856856 | N10: 110m of cable/(Total Order Qnty*3) | O10: Cu | Q10: XLPE | R10: =(P11+P13+P17+P26) -> 0.29372512
C11: WN35 | D11: =VLOOKUP(C11,'Materials List'!$B$6:$F$42,2,0) -> Non-Conductive Water Blocking | E11: 35 | F11: =+R16 -> 0.006 | G11: =E11+(E11*F11) -> 35.21 | H11: =VLOOKUP(C11,'Materials List'!$B$6:$F$53,5,0) -> 40.678454 | I11: =H11/$E$4 -> 0.69397736 | J11: =G11*H11 -> 1432.2884 | K11: =I11*G11 -> 24.434943 | L11: =J11/$J$32 -> 0.0037144518 | O11: XLPE | P11: =110/(P6*1) -> 0.11 | Q11: SC | R11: =(P11+P13+P18+P26) -> 0.29372512
C12: WN08 | D12: =VLOOKUP(C12,'Materials List'!$B$6:$F$42,2,0) -> Non-Conductive Water Blocking | E12: 55 | F12: =+R16 -> 0.006 | G12: =E12+(E12*F12) -> 55.33 | H12: =VLOOKUP(C12,'Materials List'!$B$6:$F$53,5,0) -> 33.434346 | I12: =H12/$E$4 -> 0.57039235 | J12: =G12*H12 -> 1849.9224 | K12: =I12*G12 -> 31.559809 | L12: =J12/$J$32 -> 0.0047975308 | O12: SC | Q12: CU Tape | R12: =P19+P26+P15 -> 0.036
C13: WN65 | D13: =VLOOKUP(C13,'Materials List'!$B$6:$F$42,2,0) -> Non-Conductive Water Blocking | E13: 65 | F13: =+R16 -> 0.006 | G13: =E13+(E13*F13) -> 65.39 | H13: =VLOOKUP(C13,'Materials List'!$B$6:$F$53,5,0) -> 39.006737 | I13: =H13/$E$4 -> 0.66545774 | J13: =G13*H13 -> 2550.6505 | K13: =I13*G13 -> 43.514282 | L13: =J13/$J$32 -> 0.0066147773 | N13: 150kg/(Stndard Qnty kg/km)/(Total Order Qnty*3) | O13: XLPE | P13: =(150/(E15+E16+E17)/((P6/1000*1))) -> 0.17772512 | Q13: AL Wire | R13: =P19+P26+P21 -> 0.036
C14: WS01 | D14: =VLOOKUP(C14,'Materials List'!$B$6:$F$42,2,0) -> Semi-conductive Water Blocking | E14: 85 | F14: =+R16 -> 0.006 | G14: =E14+(E14*F14) -> 85.51 | H14: =VLOOKUP(C14,'Materials List'!$B$6:$F$53,5,0) -> 132.62291 | I14: =H14/$E$4 -> 2.2625563 | J14: =G14*H14 -> 11340.585 | K14: =I14*G14 -> 193.47119 | L14: =J14/$J$32 -> 0.029410317 | O14: SC | Q14: SWA | R14: =P20+P26+P19 -> 0.036
C15: SC01 | D15: =VLOOKUP(C15,'Materials List'!$B$6:$F$42,2,0) -> Thermosetting S.C - Bonded | E15: 69 | F15: =+R11 -> 0.29372512 | G15: =E15+(E15*F15) -> 89.267033 | H15: =VLOOKUP(C15,'Materials List'!$B$6:$F$53,5,0) -> 106.38201 | I15: =H15/$E$4 -> 1.8148847 | J15: =G15*H15 -> 9496.4064 | K15: =I15*G15 -> 162.00938 | L15: =J15/$J$32 -> 0.024627683 | N15: Copper Tape | O15: CT | P15: =30/P6 -> 0.03 | Q15: Sheathing | R15: 0.01
C16: XL02 | D16: =VLOOKUP(C16,'Materials List'!$B$6:$F$42,2,0) -> XLPE Insulation For M.V Cable | E16: 691 | F16: =+R10 -> 0.29372512 | G16: =E16+(E16*F16) -> 893.96406 | H16: =VLOOKUP(C16,'Materials List'!$B$6:$F$53,5,0) -> 112.96756 | I16: =H16/$E$4 -> 1.9272348 | J16: =G16*H16 -> 100988.94 | K16: =I16*G16 -> 1722.8786 | L16: =J16/$J$32 -> 0.26190156 | N16: 0.2% of total cable | O16: CU | P16: 0.002 | Q16: All other Materials | R16: =0.4%+0.2% -> 0.006
C17: SC01 | D17: =VLOOKUP(C17,'Materials List'!$B$6:$F$42,2,0) -> Thermosetting S.C - Bonded | E17: 84 | F17: =+R11 -> 0.29372512 | G17: =E17+(E17*F17) -> 108.67291 | H17: =VLOOKUP(C17,'Materials List'!$B$6:$F$53,5,0) -> 106.38201 | I17: =H17/$E$4 -> 1.8148847 | J17: =G17*H17 -> 11560.843 | K17: =I17*G17 -> 197.22881 | L17: =J17/$J$32 -> 0.029981527 | O17: XLPE | P17: 0.002
C18: WS03 | D18: =VLOOKUP(C18,'Materials List'!$B$6:$F$42,2,0) -> Semi-conductive Water Blocking | E18: 159 | F18: =+R16 -> 0.006 | G18: =E18+(E18*F18) -> 159.954 | H18: =VLOOKUP(C18,'Materials List'!$B$6:$F$53,5,0) -> 56.113977 | I18: =H18/$E$4 -> 0.95730849 | J18: =G18*H18 -> 8975.6551 | K18: =I18*G18 -> 153.12532 | L18: =J18/$J$32 -> 0.023277183 | O18: SC | P18: 0.002
C19: CuT02 | D19: =VLOOKUP(C19,'Materials List'!$B$6:$F$42,2,0) -> Copper Tape 10x0.1mm | E19: 17 | F19: =+R12 -> 0.036 | G19: =E19+(E19*F19) -> 17.612 | H19: =VLOOKUP(C19,'Materials List'!$B$6:$F$53,5,0) -> 796.02762 | I19: =H19/$E$4 -> 13.580289 | J19: =G19*H19 -> 14019.639 | K19: =I19*G19 -> 239.17604 | L19: =J19/$J$32 -> 0.036358092 | O19: CU Tape | P19: 0.002
C20: WN81 | D20: =VLOOKUP(C20,'Materials List'!$B$6:$F$42,2,0) -> Non-Conductive Water Blocking | E20: 170 | F20: =+R16 -> 0.006 | G20: =E20+(E20*F20) -> 171.02 | H20: =VLOOKUP(C20,'Materials List'!$B$6:$F$53,5,0) -> 47.365324 | I20: =H20/$E$4 -> 0.80805583 | J20: =G20*H20 -> 8100.4176 | K20: =I20*G20 -> 138.19371 | L20: =J20/$J$32 -> 0.02100737 | N20: 30m of SWA/(Total Order Quantity) | O20: SWA | P20: =30/P6 -> 0.03
C21: PT06 | D21: =VLOOKUP(C21,'Materials List'!$B$6:$F$42,2,0) -> Polyproplyene TAPE "60 X 0.125 mm" | E21: 10.4 | F21: =+R16 -> 0.006 | G21: =E21+(E21*F21) -> 10.4624 | H21: =VLOOKUP(C21,'Materials List'!$B$6:$F$53,5,0) -> 146.90849 | I21: =H21/$E$4 -> 2.5062694 | J21: =G21*H21 -> 1537.0154 | K21: =I21*G21 -> 26.221593 | L21: =J21/$J$32 -> 0.0039860476 | N21: 30m of AWA/(Total Order Quantity) | P21: =30/P6 -> 0.03
C22: RC03 | D22: =VLOOKUP(C22,'Materials List'!$B$6:$F$42,2,0) -> RIP CORD | E22: 1.01 | F22: =+R16 -> 0.006 | G22: =E22+(E22*F22) -> 1.01606 | H22: =VLOOKUP(C22,'Materials List'!$B$6:$F$53,5,0) -> 150 | I22: =H22/$E$4 -> 2.5590108 | J22: =G22*H22 -> 152.409 | K22: =I22*G22 -> 2.6001085 | L22: =J22/$J$32 -> 0.00039525273
C23: AFD155 | D23: =VLOOKUP(C23,'Materials List'!$B$6:$F$42,2,0) -> Laminted Aluminum TAPE | E23: 85.66 | F23: =+R16 -> 0.006 | G23: =E23+(E23*F23) -> 86.17396 | H23: =VLOOKUP(C23,'Materials List'!$B$6:$F$53,5,0) -> 247.33817 | I23: =H23/$E$4 -> 4.219607 | J23: =G23*H23 -> 21314.11 | K23: =I23*G23 -> 363.62025 | L23: =J23/$J$32 -> 0.055275345
C24: PS03 | D24: =VLOOKUP(C24,'Materials List'!$B$6:$F$42,2,0) -> Medium density PE Sheath "Black" | E24: 294 | F24: =+R15 -> 0.01 | G24: =E24+(E24*F24) -> 296.94 | H24: =VLOOKUP(C24,'Materials List'!$B$6:$F$53,5,0) -> 81.05296 | I24: =H24/$E$4 -> 1.3827693 | J24: =G24*H24 -> 24067.866 | K24: =I24*G24 -> 410.59952 | L24: =J24/$J$32 -> 0.06241685
C25: A-EC04 | D25: =VLOOKUP(C25,'Materials List'!$B$6:$F$42,2,0) -> A-ECAP10 | E25: 2 | F25: =+R16 -> 0.006 | G25: =E25+(E25*F25) -> 2.012 | H25: =VLOOKUP(C25,'Materials List'!$B$6:$F$53,5,0) -> 200 | I25: =H25/$E$4 -> 3.4120144 | J25: =G25*H25 -> 402.4 | K25: =I25*G25 -> 6.8649729 | L25: =J25/$J$32 -> 0.0010435716
N26: Testing 2m+0.2% of all material/(Cutting Length) | O26: All Cable | P26: =2/(Q6)+0.2% -> 0.004
D27: 0 | E27: 1000 | G27: 0 | H27: 0 | I27: =H27/$E$4 -> 0 | J27: =H27*G27 -> 0 | K27: =I27*G27 -> 0 | L27: =J27/$J$32 -> 0
C28: Total Materials Cost | J28: =SUM(J9:J27) -> 385598.85 | K28: =SUM(K9:K27) -> 6578.3442 | L28: =SUM(L9:L27) -> 1
C29: MOH | J29: =+J28*Summary!$K$8 -> 0 | K29: =J29/$E$4 -> 0 | L29: =J29/J32 -> 0
C30: Finanace Cost | J30: =J28*Summary!$K$9 -> 0 | K30: =J30/$E$4 -> 0 | L30: =J30/$J$32 -> 0 | N30: Sales Price
C31: G&A & Marketing | J31: =J28*Summary!$K$10 -> 0 | K31: =J31/$E$4 -> 0 | L31: =J31/$J$32 -> 0 | N31: Net Profit | O31: =O30-K32 -> -6578.3442
C32: Total Cable Cost | J32: =SUM(J28:J31) -> 385598.85 | K32: =SUM(K28:K31) -> 6578.3442 | L32: =SUM(L28:L31) -> 1 | N32: % | O32: =O31/O30 -> #DIV/0!
F34: Size | G34: N.of drum | H34: length | I34: price | J34: total length | K34: Total value
G35: 0 | H35: 0 | I35: =IF($N$27="Supported",VLOOKUP(F35,#REF!,2,0)*1.25,VLOOKUP(F35,#REF!,2,0)) -> #REF! | J35: =H35*G35 -> 0 | K35: =I35*G35 -> #REF!
G36: 0 | H36: 0 | I36: =IF($N$27="Supported",VLOOKUP(F36,#REF!,2,0)*1.25,VLOOKUP(F36,#REF!,2,0)) -> #REF! | J36: =H36*G36 -> 0 | K36: =I36*G36 -> #REF!
J37: =SUM(J35:J36) -> 0 | K37: =SUM(K35:K36) -> #REF!
K38: =K37/J37*1000 -> #REF!
D39: Study | E39: Qty/KM | F39: Scrap Qty | G39: Scrap Qty
D40: Cutting Length | F40: =E40/1000*(2000-H35) -> 0 | G40: =+F40/E40 -> #DIV/0!
D41: Cutting Length | F41: =E41/1000*(2000-H36) -> 0 | G41: =+F41/E41 -> #DIV/0!
D42: Total Qty Required | E42: =+E41*K6 -> 0 | F42: =+SUM(F40:F41) -> 0 | G42: =+F42/E42 -> #DIV/0!

Sheet 4
D2: Aluminum | E2: =Summary!$D$9 -> 3239.8752
D3: Copper | E3: =Summary!$D$10 -> 14463.728
D4: =IF(Summary!H10="USD","USD Rate",IF(Summary!H10="Euro","Euro Rate","GBP Rate")) -> Euro Rate | E4: =IF(Summary!H10="USD",Summary!K5,IF(Summary!H10="GBP",Summary!K7,Summary!K6)) -> 58.6164 | J4: Cable Material Number | K4: 10010439 | P4: Order Qty | Q4: Cutting Length
D6: Cu / XLPE / MDPE 8.7/15 kV CWs 1X400/35 mm2 RMC IEC 60502-2 | J6: Qty Required | K6: =Summary!D16 -> 1 | P6: =+K6*1000 -> 1000 | Q6: =+E27 -> 1000
C8: Material Code | D8: Materails Description | E8: Standard Qty | F8: Scrap % | G8: Qty with Scrap Allow. | H8: Unit Price L.E | I8: =IF(Summary!H10="USD","Unit Price USD",IF(Summary!H10="GBP","Unit Price GBP","Unit Price Euro")) -> Unit Price Euro | J8: Value L.E | K8: =IF(Summary!H10="USD","Value USD",IF(Summary!H10="GBP","Value GBP","Value Euro")) -> Value Euro | L8: % | N8: New Scrap % | P8: New Scrap %
B9: =+IF(C9="CR01","CU",IF(C9="CR02","CU",IF(C9="AR01","AL",IF(C9="AR02","AL",IF(C9="AR08","AL",IF(C9="AR03","AL")))))) -> CU | C9: CR01 | D9: =VLOOKUP(C9,'Materials List'!$B$6:$F$42,2,0) -> Copper Rod "8mm" | E9: 3683.36 | F9: =+R9 -> 0.156 | G9: =E9+(E9*F9) -> 4257.9642 | H9: =VLOOKUP(C9,'Materials List'!$B$6:$F$53,5,0) -> 760.82025 | I9: =H9/$E$4 -> 12.979648 | J9: =G9*H9 -> 3239545.3 | K9: =I9*G9 -> 55266.876 | L9: =J9/$J$32 -> 0.94546103 | N9: 40m/(Total Order Quantity * 3) | O9: Cu | P9: =40/(P6*1) -> 0.04 | Q9: CU | R9: =P9+P11+P16+P26 -> 0.156
C10: YN01 | D10: =VLOOKUP(C10,'Materials List'!$B$6:$F$42,2,0) -> Water blocking yarn 3WY055 Tapes | E10: 5 | F10: =+R16 -> 0.006 | G10: =E10+(E10*F10) -> 5.03 | H10: =VLOOKUP(C10,'Materials List'!$B$6:$F$53,5,0) -> 1109.0223 | I10: =H10/$E$4 -> 18.92 | J10: =G10*H10 -> 5578.3821 | K10: =I10*G10 -> 95.1676 | L10: =J10/$J$32 -> 0.0016280503 | N10: 110m of cable/(Total Order Qnty*3) | O10: Cu | Q10: XLPE | R10: =(P11+P13+P17+P26) -> 0.38008451
C11: WN35 | D11: =VLOOKUP(C11,'Materials List'!$B$6:$F$42,2,0) -> Non-Conductive Water Blocking | E11: 35 | F11: =+R16 -> 0.006 | G11: =E11+(E11*F11) -> 35.21 | H11: =VLOOKUP(C11,'Materials List'!$B$6:$F$53,5,0) -> 40.678454 | I11: =H11/$E$4 -> 0.69397736 | J11: =G11*H11 -> 1432.2884 | K11: =I11*G11 -> 24.434943 | L11: =J11/$J$32 -> 0.00041801324 | O11: XLPE | P11: =110/(P6*1) -> 0.11 | Q11: SC | R11: =(P11+P13+P18+P26) -> 0.38008451
C12: WN65 | D12: =VLOOKUP(C12,'Materials List'!$B$6:$F$42,2,0) -> Non-Conductive Water Blocking | E12: 65 | F12: =+R16 -> 0.006 | G12: =E12+(E12*F12) -> 65.39 | H12: =VLOOKUP(C12,'Materials List'!$B$6:$F$53,5,0) -> 39.006737 | I12: =H12/$E$4 -> 0.66545774 | J12: =G12*H12 -> 2550.6505 | K12: =I12*G12 -> 43.514282 | L12: =J12/$J$32 -> 0.00074440714 | O12: SC | Q12: CU Tape | R12: =P19+P26+P15 -> 0.036
C13: WN75 | D13: =VLOOKUP(C13,'Materials List'!$B$6:$F$42,2,0) -> Non-Conductive Water Blocking | E13: 75 | F13: =+R16 -> 0.006 | G13: =E13+(E13*F13) -> 75.45 | H13: =VLOOKUP(C13,'Materials List'!$B$6:$F$53,5,0) -> 31.20539 | I13: =H13/$E$4 -> 0.53236619 | J13: =G13*H13 -> 2354.4466 | K13: =I13*G13 -> 40.167029 | L13: =J13/$J$32 -> 0.00068714505 | N13: 150kg/(Stndard Qnty kg/km)/(Total Order Qnty*3) | O13: XLPE | P13: =(150/(E15+E16+E17))/((P6/1000*1)) -> 0.26408451 | Q13: AL Wire | R13: =P19+P26+P21 -> 0.036
C14: WS01 | D14: =VLOOKUP(C14,'Materials List'!$B$6:$F$42,2,0) -> Semi-conductive Water Blocking | E14: 95 | F14: =+R16 -> 0.006 | G14: =E14+(E14*F14) -> 95.57 | H14: =VLOOKUP(C14,'Materials List'!$B$6:$F$53,5,0) -> 132.62291 | I14: =H14/$E$4 -> 2.2625563 | J14: =G14*H14 -> 12674.771 | K14: =I14*G14 -> 216.23251 | L14: =J14/$J$32 -> 0.0036991308 | O14: SC | Q14: SWA | R14: =P20+P26+P19 -> 0.036
C15: SC01 | D15: =VLOOKUP(C15,'Materials List'!$B$6:$F$42,2,0) -> Thermosetting S.C - Bonded | E15: 86 | F15: =+R11 -> 0.38008451 | G15: =E15+(E15*F15) -> 118.68727 | H15: =VLOOKUP(C15,'Materials List'!$B$6:$F$53,5,0) -> 106.38201 | I15: =H15/$E$4 -> 1.8148847 | J15: =G15*H15 -> 12626.19 | K15: =I15*G15 -> 215.40371 | L15: =J15/$J$32 -> 0.0036849525 | N15: Copper Tape | O15: CT | P15: =30/P6 -> 0.03 | Q15: Sheathing | R15: 0.01
C16: XL02 | D16: =VLOOKUP(C16,'Materials List'!$B$6:$F$42,2,0) -> XLPE Insulation For M.V Cable | E16: 366 | F16: =+R10 -> 0.38008451 | G16: =E16+(E16*F16) -> 505.11093 | H16: =VLOOKUP(C16,'Materials List'!$B$6:$F$53,5,0) -> 112.96756 | I16: =H16/$E$4 -> 1.9272348 | J16: =G16*H16 -> 57061.151 | K16: =I16*G16 -> 973.46734 | L16: =J16/$J$32 -> 0.016653292 | N16: 0.2% of total cable | O16: CU | P16: 0.002 | Q16: All other Materials | R16: =0.4%+0.2% -> 0.006
C17: SC02 | D17: =VLOOKUP(C17,'Materials List'!$B$6:$F$42,2,0) -> Thermosetting S.C - Strippable | E17: 116 | F17: =+R11 -> 0.38008451 | G17: =E17+(E17*F17) -> 160.0898 | H17: =VLOOKUP(C17,'Materials List'!$B$6:$F$53,5,0) -> 124.36564 | I17: =H17/$E$4 -> 2.1216867 | J17: =G17*H17 -> 19909.67 | K17: =I17*G17 -> 339.6604 | L17: =J17/$J$32 -> 0.0058106355 | O17: XLPE | P17: 0.002
C18: WS03 | D18: =VLOOKUP(C18,'Materials List'!$B$6:$F$42,2,0) -> Semi-conductive Water Blocking | E18: 143 | F18: =+R16 -> 0.006 | G18: =E18+(E18*F18) -> 143.858 | H18: =VLOOKUP(C18,'Materials List'!$B$6:$F$53,5,0) -> 56.113977 | I18: =H18/$E$4 -> 0.95730849 | J18: =G18*H18 -> 8072.4446 | K18: =I18*G18 -> 137.71648 | L18: =J18/$J$32 -> 0.0023559422 | O18: SC | P18: 0.002
C19: CuT02 | D19: =VLOOKUP(C19,'Materials List'!$B$6:$F$42,2,0) -> Copper Tape 10x0.1mm | E19: 17 | F19: =+R12 -> 0.036 | G19: =E19+(E19*F19) -> 17.612 | H19: =VLOOKUP(C19,'Materials List'!$B$6:$F$53,5,0) -> 796.02762 | I19: =H19/$E$4 -> 13.580289 | J19: =G19*H19 -> 14019.639 | K19: =I19*G19 -> 239.17604 | L19: =J19/$J$32 -> 0.0040916303 | O19: CU Tape | P19: 0.002
C20: WN03 | D20: =VLOOKUP(C20,'Materials List'!$B$6:$F$42,2,0) -> Non-Conductive Water Blocking | E20: 156 | F20: =+R16 -> 0.006 | G20: =E20+(E20*F20) -> 156.936 | H20: =VLOOKUP(C20,'Materials List'!$B$6:$F$53,5,0) -> 47.365324 | I20: =H20/$E$4 -> 0.80805583 | J20: =G20*H20 -> 7433.3244 | K20: =I20*G20 -> 126.81305 | L20: =J20/$J$32 -> 0.0021694151 | N20: 30m of SWA/(Total Order Quantity) | O20: SWA | P20: =30/P6 -> 0.03
C21: PT04 | D21: =VLOOKUP(C21,'Materials List'!$B$6:$F$42,2,0) -> Poly Propylene Tape "40 X 0.125 mm" | E21: 9.59 | F21: =+R16 -> 0.006 | G21: =E21+(E21*F21) -> 9.64754 | H21: =VLOOKUP(C21,'Materials List'!$B$6:$F$53,5,0) -> 146.90849 | I21: =H21/$E$4 -> 2.5062694 | J21: =G21*H21 -> 1417.3055 | K21: =I21*G21 -> 24.179334 | L21: =J21/$J$32 -> 0.0004136405 | N21: 30m of AWA/(Total Order Quantity) | P21: =30/P6 -> 0.03
C22: RC03 | D22: =VLOOKUP(C22,'Materials List'!$B$6:$F$42,2,0) -> RIP CORD | E22: 1.01 | F22: =+R16 -> 0.006 | G22: =E22+(E22*F22) -> 1.01606 | H22: =VLOOKUP(C22,'Materials List'!$B$6:$F$53,5,0) -> 150 | I22: =H22/$E$4 -> 2.5590108 | J22: =G22*H22 -> 152.409 | K22: =I22*G22 -> 2.6001085 | L22: =J22/$J$32 -> 4.4480553e-05
C23: AFD145 | D23: =VLOOKUP(C23,'Materials List'!$B$6:$F$42,2,0) -> Laminted Aluminum TAPE | E23: 80.65 | F23: =+R16 -> 0.006 | G23: =E23+(E23*F23) -> 81.1339 | H23: =VLOOKUP(C23,'Materials List'!$B$6:$F$53,5,0) -> 247.33817 | I23: =H23/$E$4 -> 4.219607 | J23: =G23*H23 -> 20067.511 | K23: =I23*G23 -> 342.35317 | L23: =J23/$J$32 -> 0.0058567012
C24: PS03 | D24: =VLOOKUP(C24,'Materials List'!$B$6:$F$42,2,0) -> Medium density PE Sheath "Black" | E24: 258 | F24: =+R15 -> 0.01 | G24: =E24+(E24*F24) -> 260.58 | H24: =VLOOKUP(C24,'Materials List'!$B$6:$F$53,5,0) -> 81.05296 | I24: =H24/$E$4 -> 1.3827693 | J24: =G24*H24 -> 21120.78 | K24: =I24*G24 -> 360.32203 | L24: =J24/$J$32 -> 0.0061640979
C25: A-EC04 | D25: =VLOOKUP(C25,'Materials List'!$B$6:$F$42,2,0) -> A-ECAP10 | E25: 2 | F25: =+R16 -> 0.006 | G25: =E25+(E25*F25) -> 2.012 | H25: =VLOOKUP(C25,'Materials List'!$B$6:$F$53,5,0) -> 200 | I25: =H25/$E$4 -> 3.4120144 | J25: =G25*H25 -> 402.4 | K25: =I25*G25 -> 6.8649729 | L25: =J25/$J$32 -> 0.00011744041
N26: Testing 2m+0.2% of all material/(Cutting Length) | O26: All Cable | P26: =2/(Q6)+0.2% -> 0.004
E27: 1000 | I27: =H27/$E$4 -> 0 | J27: =H27*G27 -> 0 | K27: =I27*G27 -> 0 | L27: =J27/$J$32 -> 0
C28: Total Materials Cost | J28: =SUM(J9:J27) -> 3426418.7 | K28: =SUM(K9:K27) -> 58454.949 | L28: =SUM(L9:L27) -> 1
C29: MOH | J29: =+J28*Summary!$K$8 -> 0 | K29: =J29/$E$4 -> 0 | L29: =J29/J32 -> 0
C30: Finanace Cost | J30: =J28*Summary!$K$9 -> 0 | K30: =J30/$E$4 -> 0 | L30: =J30/$J$32 -> 0 | N30: Sales Price
C31: G&A & Marketing | J31: =J28*Summary!$K$10 -> 0 | K31: =J31/$E$4 -> 0 | L31: =J31/$J$32 -> 0 | N31: Net Profit | O31: =O30-K32 -> -58454.949
C32: Total Cable Cost | J32: =SUM(J28:J31) -> 3426418.7 | K32: =SUM(K28:K31) -> 58454.949 | L32: =SUM(L28:L31) -> 1 | N32: % | O32: =O31/O30 -> #DIV/0!
F34: Size | G34: N.of drum | H34: length | I34: price | J34: total length | K34: Total value
G35: 0 | H35: 0 | I35: =IF($N$27="Supported",VLOOKUP(F35,#REF!,2,0)*1.25,VLOOKUP(F35,#REF!,2,0)) -> #REF! | J35: =H35*G35 -> 0 | K35: =I35*G35 -> #REF!
G36: 0 | H36: 0 | I36: =IF($N$27="Supported",VLOOKUP(F36,#REF!,2,0)*1.25,VLOOKUP(F36,#REF!,2,0)) -> #REF! | J36: =H36*G36 -> 0 | K36: =I36*G36 -> #REF!
J37: =SUM(J35:J36) -> 0 | K37: =SUM(K35:K36) -> #REF!
K38: =K37/J37*1000 -> #REF!
D39: Study | E39: Qty/KM | F39: Scrap Qty | G39: Scrap Qty
D40: Cutting Length | F40: =E40/1000*(2000-H35) -> 0 | G40: =+F40/E40 -> #DIV/0!
D41: Cutting Length | F41: =E41/1000*(2000-H36) -> 0 | G41: =+F41/E41 -> #DIV/0!
D42: Total Qty Required | E42: =+E41*K6 -> 0 | F42: =+SUM(F40:F41) -> 0 | G42: =+F42/E42 -> #DIV/0!
